ulises/__main__.py
ulises/containerscli.py
ulises/imagescli.py
ulises/maincli.py
ulises/subcli.py
ulises/volumescli.py
ulises-1.0.0.dist-info/LICENSE
ulises-1.0.0.dist-info/METADATA
ulises-1.0.0.dist-info/WHEEL
ulises-1.0.0.dist-info/entry_points.txt
ulises-1.0.0.dist-info/top_level.txt
ulises-1.0.0.dist-info/RECORD
