Metadata-Version: 2.1
Name: ulises
Version: 1.0.0
Summary: Makes managing Docker resources a nice experience
Author-email: Carlos del Ojo <carlos@delojo.me>
License: GNU GENERAL PUBLIC LICENSE
Project-URL: Homepage, https://github.com/coelias/ulises
Keywords: docker,UI,CLI
Classifier: License :: OSI Approved :: GNU General Public License v3 (GPLv3)
Classifier: Programming Language :: Python
Classifier: Programming Language :: Python :: 3
Classifier: Environment :: Console
Classifier: Intended Audience :: System Administrators
Classifier: Intended Audience :: Developers
Classifier: Topic :: System :: Systems Administration
Requires-Python: >=3.9
License-File: LICENSE
Requires-Dist: docker (==5.0.3)
Requires-Dist: rich (==12.3.)
Requires-Dist: tomli ; python_version < "3.11"
